gpt_oss_redteam/__init__.py
gpt_oss_redteam/analysis.py
gpt_oss_redteam/aws_ollama_redteam_notebook.py
gpt_oss_redteam/cli.py
gpt_oss_redteam/deepseek.py
gpt_oss_redteam/ollama_client.py
gpt_oss_redteam/ollama_gen.py
gpt_oss_redteam/pipeline.py
gpt_oss_redteam/tools.py
gpt_oss_redteam/utils.py
gpt_oss_redteam-0.1.3.dist-info/METADATA
gpt_oss_redteam-0.1.3.dist-info/WHEEL
gpt_oss_redteam-0.1.3.dist-info/entry_points.txt
gpt_oss_redteam-0.1.3.dist-info/licenses/LICENSE
gpt_oss_redteam-0.1.3.dist-info/RECORD
