Metadata-Version: 2.4
Name: gpt-oss-redteam
Version: 0.1.3
Summary: Simple, reproducible red teaming pipeline for GPT-OSS via Ollama with DeepSeek-based prompt generation
Project-URL: Homepage, https://github.com/kpower7/gpt-oss-redteam
Project-URL: Documentation, https://github.com/kpower7/gpt-oss-redteam
Author: K Power
License: MIT
License-File: LICENSE
Classifier: License :: OSI Approved :: MIT License
Classifier: Operating System :: OS Independent
Classifier: Programming Language :: Python :: 3
Requires-Python: >=3.9
Requires-Dist: openai>=1.44.0
Requires-Dist: tqdm>=4.66.0
